[   
   {"productCode":1101,"warehouseCode":"101","availableQty":"1500","inStockStatus":"forceInStock","catalog":"us-product-catalog","maxPreOrder":"0","maxStockLevelHistoryCount":"10","overSelling":"0","preOrder":"0","reserved":"0"},
   {"productCode":1101,"warehouseCode":"101","availableQty":"1500","inStockStatus":"forceInStock","catalog":"us-product-catalog","maxPreOrder":"0","maxStockLevelHistoryCount":"10","overSelling":"0","preOrder":"0","reserved":"0"},
   {"productCode":1101,"warehouseCode":"101","availableQty":"1500","inStockStatus":"forceInStock","catalog":"us-product-catalog","maxPreOrder":"0","maxStockLevelHistoryCount":"10","overSelling":"0","preOrder":"0","reserved":"0"},
   {"productCode":1102,"warehouseCode":"101","availableQty":"500","inStockStatus":"forceInStock","catalog":"us-product-catalog","maxPreOrder":"0","maxStockLevelHistoryCount":"10","overSelling":"0","preOrder":"0","reserved":"0"},
   {"productCode":1103,"warehouseCode":"101","availableQty":"100","inStockStatus":"notSpecified","catalog":"us-product-catalog","maxPreOrder":"0","maxStockLevelHistoryCount":"10","overSelling":"0","preOrder":"0","reserved":"0"},
   {"productCode":1104,"warehouseCode":"101","availableQty":"2500","inStockStatus":"notSpecified","catalog":"us-product-catalog","maxPreOrder":"0","maxStockLevelHistoryCount":"10","overSelling":"0","preOrder":"0","reserved":"0"},
   {"productCode":1105,"warehouseCode":"101","availableQty":"200","inStockStatus":"notSpecified","catalog":"us-product-catalog","maxPreOrder":"0","maxStockLevelHistoryCount":"10","overSelling":"0","preOrder":"0","reserved":"0"},
   {"productCode":1106,"warehouseCode":"101","availableQty":"500","inStockStatus":"notSpecified","catalog":"us-product-catalog","maxPreOrder":"0","maxStockLevelHistoryCount":"10","overSelling":"0","preOrder":"0","reserved":"0"},
   {"productCode":1107,"warehouseCode":"101","availableQty":"3500","inStockStatus":"notSpecified","catalog":"us-product-catalog","maxPreOrder":"0","maxStockLevelHistoryCount":"10","overSelling":"0","preOrder":"0","reserved":"0"},
   {"productCode":1108,"warehouseCode":"101","availableQty":"0","inStockStatus":"outOfStock","catalog":"us-product-catalog","maxPreOrder":"0","maxStockLevelHistoryCount":"10","overSelling":"0","preOrder":"0","reserved":"0"},
   {"productCode":1109,"warehouseCode":"101","availableQty":"10","inStockStatus":"notSpecified","catalog":"us-product-catalog","maxPreOrder":"0","maxStockLevelHistoryCount":"10","overSelling":"0","preOrder":"0","reserved":"0"},
   {"productCode":1110,"warehouseCode":"101","availableQty":"500","inStockStatus":"notSpecified","catalog":"us-product-catalog","maxPreOrder":"0","maxStockLevelHistoryCount":"10","overSelling":"0","preOrder":"0","reserved":"0"},
   {"productCode":1111,"warehouseCode":"102","availableQty":"50","inStockStatus":"notSpecified","catalog":"us-product-catalog","maxPreOrder":"0","maxStockLevelHistoryCount":"10","overSelling":"0","preOrder":"0","reserved":"0"},
   {"productCode":1112,"warehouseCode":"102","availableQty":"2500","inStockStatus":"notSpecified","catalog":"us-product-catalog","maxPreOrder":"0","maxStockLevelHistoryCount":"10","overSelling":"0","preOrder":"0","reserved":"0"},
   {"productCode":1113,"warehouseCode":"102","availableQty":"3500","inStockStatus":"notSpecified","catalog":"us-product-catalog","maxPreOrder":"0","maxStockLevelHistoryCount":"10","overSelling":"0","preOrder":"0","reserved":"0"},
   {"productCode":1114,"warehouseCode":"102","availableQty":"15500","inStockStatus":"notSpecified","catalog":"us-product-catalog","maxPreOrder":"0","maxStockLevelHistoryCount":"10","overSelling":"0","preOrder":"0","reserved":"0"},
   {"productCode":1115,"warehouseCode":"102","availableQty":"4500","inStockStatus":"notSpecified","catalog":"us-product-catalog","maxPreOrder":"0","maxStockLevelHistoryCount":"10","overSelling":"0","preOrder":"0","reserved":"0"},
   {"productCode":1116,"warehouseCode":"102","availableQty":"1500","inStockStatus":"notSpecified","catalog":"us-product-catalog","maxPreOrder":"0","maxStockLevelHistoryCount":"10","overSelling":"0","preOrder":"0","reserved":"0"},
   {"productCode":1117,"warehouseCode":"102","availableQty":"2500","inStockStatus":"forceInStock","catalog":"us-product-catalog","maxPreOrder":"0","maxStockLevelHistoryCount":"10","overSelling":"0","preOrder":"0","reserved":"0"},
   {"productCode":1118,"warehouseCode":"102","availableQty":"3500","inStockStatus":"forceInStock","catalog":"us-product-catalog","maxPreOrder":"0","maxStockLevelHistoryCount":"10","overSelling":"0","preOrder":"0","reserved":"0"},
   {"productCode":1119,"warehouseCode":"102","availableQty":"1000","inStockStatus":"forceInStock","catalog":"us-product-catalog","maxPreOrder":"0","maxStockLevelHistoryCount":"10","overSelling":"0","preOrder":"0","reserved":"0"},
   {"productCode":1120,"warehouseCode":"102","availableQty":"0","inStockStatus":"outOfStock","catalog":"us-product-catalog","maxPreOrder":"0","maxStockLevelHistoryCount":"10","overSelling":"0","preOrder":"0","reserved":"0"},

   {"productCode":3101001,"warehouseCode":"102","availableQty":"1000","inStockStatus":"forceInStock","catalog":"us-product-catalog","maxPreOrder":"0","maxStockLevelHistoryCount":"10","overSelling":"0","preOrder":"0","reserved":"0"},
   {"productCode":3101002,"warehouseCode":"102","availableQty":"500","inStockStatus":"forceInStock","catalog":"us-product-catalog","maxPreOrder":"0","maxStockLevelHistoryCount":"10","overSelling":"0","preOrder":"0","reserved":"0"},
   {"productCode":3102001,"warehouseCode":"102","availableQty":"1000","inStockStatus":"forceInStock","catalog":"us-product-catalog","maxPreOrder":"0","maxStockLevelHistoryCount":"10","overSelling":"0","preOrder":"0","reserved":"0"},
   {"productCode":3102002,"warehouseCode":"102","availableQty":"500","inStockStatus":"forceInStock","catalog":"us-product-catalog","maxPreOrder":"0","maxStockLevelHistoryCount":"10","overSelling":"0","preOrder":"0","reserved":"0"},
   {"productCode":3103001,"warehouseCode":"102","availableQty":"1000","inStockStatus":"forceInStock","catalog":"us-product-catalog","maxPreOrder":"0","maxStockLevelHistoryCount":"10","overSelling":"0","preOrder":"0","reserved":"0"},
   {"productCode":3103002,"warehouseCode":"102","availableQty":"500","inStockStatus":"forceInStock","catalog":"us-product-catalog","maxPreOrder":"0","maxStockLevelHistoryCount":"10","overSelling":"0","preOrder":"0","reserved":"0"},
   {"productCode":3104001,"warehouseCode":"102","availableQty":"1000","inStockStatus":"forceInStock","catalog":"us-product-catalog","maxPreOrder":"0","maxStockLevelHistoryCount":"10","overSelling":"0","preOrder":"0","reserved":"0"},
   {"productCode":3104002,"warehouseCode":"102","availableQty":"500","inStockStatus":"forceInStock","catalog":"us-product-catalog","maxPreOrder":"0","maxStockLevelHistoryCount":"10","overSelling":"0","preOrder":"0","reserved":"0"},
   
   {"productCode":3101001001,"warehouseCode":"102","availableQty":"1000","inStockStatus":"forceInStock","catalog":"us-product-catalog","maxPreOrder":"0","maxStockLevelHistoryCount":"10","overSelling":"0","preOrder":"0","reserved":"0"},
   {"productCode":3101002001,"warehouseCode":"102","availableQty":"500","inStockStatus":"forceInStock","catalog":"us-product-catalog","maxPreOrder":"0","maxStockLevelHistoryCount":"10","overSelling":"0","preOrder":"0","reserved":"0"},
   {"productCode":3102001001,"warehouseCode":"102","availableQty":"1000","inStockStatus":"forceInStock","catalog":"us-product-catalog","maxPreOrder":"0","maxStockLevelHistoryCount":"10","overSelling":"0","preOrder":"0","reserved":"0"},
   {"productCode":3102002001,"warehouseCode":"102","availableQty":"500","inStockStatus":"forceInStock","catalog":"us-product-catalog","maxPreOrder":"0","maxStockLevelHistoryCount":"10","overSelling":"0","preOrder":"0","reserved":"0"},
   {"productCode":3103001001,"warehouseCode":"102","availableQty":"1000","inStockStatus":"forceInStock","catalog":"us-product-catalog","maxPreOrder":"0","maxStockLevelHistoryCount":"10","overSelling":"0","preOrder":"0","reserved":"0"},
   {"productCode":3103002001,"warehouseCode":"102","availableQty":"500","inStockStatus":"forceInStock","catalog":"us-product-catalog","maxPreOrder":"0","maxStockLevelHistoryCount":"10","overSelling":"0","preOrder":"0","reserved":"0"},
   {"productCode":3104001001,"warehouseCode":"102","availableQty":"1000","inStockStatus":"forceInStock","catalog":"us-product-catalog","maxPreOrder":"0","maxStockLevelHistoryCount":"10","overSelling":"0","preOrder":"0","reserved":"0"},
   {"productCode":3104002001,"warehouseCode":"102","availableQty":"500","inStockStatus":"forceInStock","catalog":"us-product-catalog","maxPreOrder":"0","maxStockLevelHistoryCount":"10","overSelling":"0","preOrder":"0","reserved":"0"},

   {"productCode":3101001002,"warehouseCode":"102","availableQty":"1000","inStockStatus":"forceInStock","catalog":"us-product-catalog","maxPreOrder":"0","maxStockLevelHistoryCount":"10","overSelling":"0","preOrder":"0","reserved":"0"},
   {"productCode":3101002002,"warehouseCode":"102","availableQty":"500","inStockStatus":"forceInStock","catalog":"us-product-catalog","maxPreOrder":"0","maxStockLevelHistoryCount":"10","overSelling":"0","preOrder":"0","reserved":"0"},
   {"productCode":3102001002,"warehouseCode":"102","availableQty":"1000","inStockStatus":"forceInStock","catalog":"us-product-catalog","maxPreOrder":"0","maxStockLevelHistoryCount":"10","overSelling":"0","preOrder":"0","reserved":"0"},
   {"productCode":3102002002,"warehouseCode":"102","availableQty":"500","inStockStatus":"forceInStock","catalog":"us-product-catalog","maxPreOrder":"0","maxStockLevelHistoryCount":"10","overSelling":"0","preOrder":"0","reserved":"0"},
   {"productCode":3103001002,"warehouseCode":"102","availableQty":"1000","inStockStatus":"forceInStock","catalog":"us-product-catalog","maxPreOrder":"0","maxStockLevelHistoryCount":"10","overSelling":"0","preOrder":"0","reserved":"0"},
   {"productCode":3103002002,"warehouseCode":"102","availableQty":"500","inStockStatus":"forceInStock","catalog":"us-product-catalog","maxPreOrder":"0","maxStockLevelHistoryCount":"10","overSelling":"0","preOrder":"0","reserved":"0"},
   {"productCode":3104001002,"warehouseCode":"102","availableQty":"1000","inStockStatus":"forceInStock","catalog":"us-product-catalog","maxPreOrder":"0","maxStockLevelHistoryCount":"10","overSelling":"0","preOrder":"0","reserved":"0"},
   {"productCode":3104002002,"warehouseCode":"102","availableQty":"500","inStockStatus":"forceInStock","catalog":"us-product-catalog","maxPreOrder":"0","maxStockLevelHistoryCount":"10","overSelling":"0","preOrder":"0","reserved":"0"}


]